cython_build_helper/__init__.py
cython_build_helper/build_helper.py
cython_build_helper-0.4.0.dist-info/METADATA
cython_build_helper-0.4.0.dist-info/WHEEL
cython_build_helper-0.4.0.dist-info/top_level.txt
cython_build_helper-0.4.0.dist-info/RECORD
