Metadata-Version: 2.1
Name: cython-build-helper
Version: 0.4.0
Summary: A helper for building Cython projects with flexible file copying and module building.
Home-page: https://github.com/xfally/cython-build-helper
Author: xfally
Author-email: coolwinding@foxmail.com
Requires-Python: >=3.6
Requires-Dist: Cython >=3.0.12
